git_workon/__init__.py
git_workon/cli.py
git_workon/config.py
git_workon/git.py
git_workon-3.1.0.dist-info/LICENSE
git_workon-3.1.0.dist-info/METADATA
git_workon-3.1.0.dist-info/WHEEL
git_workon-3.1.0.dist-info/entry_points.txt
git_workon-3.1.0.dist-info/RECORD
