Metadata-Version: 2.1
Name: git-workon
Version: 3.1.0
Summary: Utility that automates projects clone/remove and checks for nonpushed changes on removal
Home-page: https://github.com/ReturnedVoid/workon
License: MIT
Author: Andrey Nechaev
Author-email: andrewnech@gmail.com
Requires-Python: >=3.7,<4.0
Classifier: Development Status :: 5 - Production/Stable
Classifier: Environment :: Console
Classifier: Intended Audience :: End Users/Desktop
Classifier: License :: OSI Approved :: MIT License
Classifier: Operating System :: POSIX :: Linux
Classifier: Programming Language :: Python :: 3
Classifier: Programming Language :: Python :: 3.7
Classifier: Programming Language :: Python :: 3.8
Classifier: Programming Language :: Python :: 3.9
Classifier: Programming Language :: Python :: 3.10
Classifier: Programming Language :: Python :: 3.11
Classifier: Topic :: Utilities
Requires-Dist: appdirs (>=1.4.4,<2.0.0)
Requires-Dist: termcolor (>=1.1.0,<2.0.0)
Project-URL: Repository, https://github.com/ReturnedVoid/workon
